stun_protocol/__init__.py
stun_protocol/attribute.py
stun_protocol/message.py
stun_protocol/stun.py
tests/__init__.py
tests/test_attribute.py
tests/test_message.py
stun_protocol-0.0.8.dist-info/LICENSE
stun_protocol-0.0.8.dist-info/METADATA
stun_protocol-0.0.8.dist-info/WHEEL
stun_protocol-0.0.8.dist-info/top_level.txt
stun_protocol-0.0.8.dist-info/RECORD
