Metadata-Version: 2.1
Name: stun-protocol
Version: 0.0.8
Summary: A package for creating, parsing, and serializing STUN (RFC8489) packets
Home-page: https://github.com/nbuckles13/python-stun-protocol
Author: Carl Nathan Buckles
Author-email: nbuckles@gmail.com
Project-URL: Bug Tracker, https://github.com/nbuckles13/python-stun-protocol/issues
Classifier: Programming Language :: Python :: 3
Classifier: License :: OSI Approved :: MIT License
Classifier: Operating System :: OS Independent
Requires-Python: >=3.6
License-File: LICENSE
